How2jQianduanJiaochengFix1/README.md
How2jQianduanJiaochengFix1/__init__.py
How2jQianduanJiaochengFix1/__main__.py
How2jQianduanJiaochengFix1/file.epub
How2jQianduanJiaochengFix1/index.html
How2jQianduanJiaochengFix1/css/__init__.py
How2jQianduanJiaochengFix1/css/annotations.css
How2jQianduanJiaochengFix1/css/main.css
How2jQianduanJiaochengFix1/css/normalize.css
How2jQianduanJiaochengFix1/css/popup.css
How2jQianduanJiaochengFix1/font/__init__.py
How2jQianduanJiaochengFix1/font/fontello.eot
How2jQianduanJiaochengFix1/font/fontello.svg
How2jQianduanJiaochengFix1/font/fontello.ttf
How2jQianduanJiaochengFix1/font/fontello.woff
How2jQianduanJiaochengFix1/img/__init__.py
How2jQianduanJiaochengFix1/img/annotator-glyph-sprite.png
How2jQianduanJiaochengFix1/img/annotator-icon-sprite.png
How2jQianduanJiaochengFix1/img/apple-touch-icon.png
How2jQianduanJiaochengFix1/img/cancelfullscreen.png
How2jQianduanJiaochengFix1/img/close.png
How2jQianduanJiaochengFix1/img/fullscreen.png
How2jQianduanJiaochengFix1/img/loader.gif
How2jQianduanJiaochengFix1/img/menu-icon.png
How2jQianduanJiaochengFix1/img/save.png
How2jQianduanJiaochengFix1/img/saved.png
How2jQianduanJiaochengFix1/img/settings-s.png
How2jQianduanJiaochengFix1/img/settings.png
How2jQianduanJiaochengFix1/img/star.png
How2jQianduanJiaochengFix1/js/__init__.py
How2jQianduanJiaochengFix1/js/epub.js
How2jQianduanJiaochengFix1/js/epub.min.js
How2jQianduanJiaochengFix1/js/epub.min.map
How2jQianduanJiaochengFix1/js/hooks.min.js
How2jQianduanJiaochengFix1/js/hooks.min.map
How2jQianduanJiaochengFix1/js/reader.js
How2jQianduanJiaochengFix1/js/reader.js.map
How2jQianduanJiaochengFix1/js/reader.min.js
How2jQianduanJiaochengFix1/js/reader.min.map
How2jQianduanJiaochengFix1/js/hooks/__init__.py
How2jQianduanJiaochengFix1/js/hooks/extensions/__init__.py
How2jQianduanJiaochengFix1/js/hooks/extensions/highlight.js
How2jQianduanJiaochengFix1/js/libs/__init__.py
How2jQianduanJiaochengFix1/js/libs/jquery.min.js
how2j_qianduan_jiaocheng_fix1-2025.3.25.0.dist-info/METADATA
how2j_qianduan_jiaocheng_fix1-2025.3.25.0.dist-info/WHEEL
how2j_qianduan_jiaocheng_fix1-2025.3.25.0.dist-info/entry_points.txt
how2j_qianduan_jiaocheng_fix1-2025.3.25.0.dist-info/top_level.txt
how2j_qianduan_jiaocheng_fix1-2025.3.25.0.dist-info/RECORD
